sportmonks_py/__init__.py
sportmonks_py/api_client.py
sportmonks_py/base_client.py
sportmonks_py/core/__init__.py
sportmonks_py/core/common_types.py
sportmonks_py/core/custom_exceptions.py
sportmonks_py/core/filters.py
sportmonks_py/core/utils.py
sportmonks_py/cricket/__init__.py
sportmonks_py/football/__init__.py
sportmonks_py/football/common.py
sportmonks_py/football/fixture.py
sportmonks_py/football/leagues.py
sportmonks_py/football/misc.py
sportmonks_py/football/odds.py
sportmonks_py/football/standings.py
sportmonks_py/football/statistics.py
sportmonks_py/football/teams.py
sportmonks_py/formula1/__init__.py
sportmonks_py-0.1.dist-info/METADATA
sportmonks_py-0.1.dist-info/WHEEL
sportmonks_py-0.1.dist-info/licenses/LICENSE
sportmonks_py-0.1.dist-info/RECORD
