Metadata-Version: 2.3
Name: sportmonks-py
Version: 0.1
Summary: A Python package to interact with the SportMonks API
Project-URL: Repository, https://github.com/cmccallan/sportmonks-py
Project-URL: Issues, https://github.com/cmccallan/sportmonks-py/issues
Project-URL: Changelog, https://github.com/cmccallan/sportmonks-py/blob/main/changelog
Author: Chris McCallan
Maintainer-email: Chris McCallan <chris.mccallan+sportmonks@hotmail.co.uk>
License: MIT License
Keywords: api,apiv3,data,football,soccer,sportmonks
Requires-Python: >=3.9
Requires-Dist: arrow>=1.3.0
Requires-Dist: datetime>=5.5
Requires-Dist: http-client>=0.1.22
Requires-Dist: logging>=0.4.9.6
Requires-Dist: pandas>=2.2.3
Requires-Dist: polars>=1.14.0
Requires-Dist: pytest>=8.3.3
Requires-Dist: pytz>=2024.2
Requires-Dist: responses>=0.25.3
Requires-Dist: ruff>=0.8.2
Requires-Dist: tzlocal>=5.2
